{
  "_comment": "Korte code -> {title, artist, year, spotify, previewUrl?}. previewUrl is optioneel; de pagina zoekt 'm anders zelf op via iTunes.",
  "j3w": {
    "title": "Spijt",
    "artist": "Roxy Dekker",
    "year": 2022,
    "spotify": "0RHUZb0zXTARrtYjstHYcP"
  },
  "w9r": {
    "title": "Heimwee",
    "artist": "STEFF & Roxy Dekker",
    "year": 2022,
    "spotify": "4cGc0pC5zea38YjqtVNGLa"
  },
  "ab1": {
    "title": "100%",
    "artist": "FLEMMING & Mart Hoogkamer",
    "year": 2023,
    "spotify": "1lzzSzBejW6m8UN2PdRsDv"
  },
  "6ob": {
    "title": "Sugardaddy",
    "artist": "Roxy Dekker",
    "year": 2024,
    "spotify": "2hIFhSltVcRU1oJ3kf8Zy4"
  },
  "77k": {
    "title": "Satisfyer",
    "artist": "Roxy Dekker",
    "year": 2023,
    "spotify": "3qbb77qMxI5v013fqfRUzc"
  },
  "9gv": {
    "title": "Ga Dan!",
    "artist": "Roxy Dekker",
    "year": 2025,
    "spotify": "62iG1lk8qtd26ldgzCdRh5"
  },
  "2ff": {
    "title": "Gaan We Weg?",
    "artist": "Roxy Dekker",
    "year": 2024,
    "spotify": "02nm2yGw7BygWmRcbFhAlC"
  },
  "ad6": {
    "title": "Anne-Fleur Vakantie",
    "artist": "Roxy Dekker",
    "year": 2023,
    "spotify": "0omaeI4JjN2g5vHBCZHqUJ"
  },
  "rsx": {
    "title": "Industry Plant",
    "artist": "Roxy Dekker",
    "year": 2024,
    "spotify": "31EsbpCFl01yQtLncNdjSz"
  },
  "yj9": {
    "title": "Hoe Het Is",
    "artist": "Roxy Dekker",
    "year": 2025,
    "spotify": "7osE6MJVDWyX9XUVC7Q242"
  },
  "6bx": {
    "title": "Casual",
    "artist": "Roxy Dekker",
    "year": 2025,
    "spotify": "1Oq4ei25SeGivbXLcCnz7z"
  },
  "bq7": {
    "title": "Proost",
    "artist": "Roxy Dekker",
    "year": 2025,
    "spotify": "0KfKG23F2eWsq3iJazXYvS"
  },
  "x3x": {
    "title": "1 Nacht",
    "artist": "Roxy Dekker & Koen",
    "year": 2025,
    "spotify": "2dUJ0xW4XC89CC6gD7mjwi"
  },
  "92v": {
    "title": "Guilty Pleasure",
    "artist": "Roxy Dekker & Russo",
    "year": 2025,
    "spotify": "2TXDgE4nZbwdbfAW7Tr6Ll"
  },
  "fe6": {
    "title": "Over Datum",
    "artist": "Roxy Dekker",
    "year": 2025,
    "spotify": "4KCbrGjAVjAN6ZmvHtcDtX"
  },
  "86s": {
    "title": "Jouw Idee",
    "artist": "Roxy Dekker",
    "year": 2025,
    "spotify": "6u9MrPWzCXj0pQjuglCyqy"
  },
  "w2v": {
    "title": "Loser",
    "artist": "Roxy Dekker",
    "year": 2025,
    "spotify": "6SxPeeIm0exX9vXLZMZn2J"
  },
  "gf9": {
    "title": "Cool",
    "artist": "Roxy Dekker",
    "year": 2025,
    "spotify": "7p1HMiOlr5YSldteisHWZe"
  },
  "qeo": {
    "title": "Down 4 Whatever",
    "artist": "Roxy Dekker",
    "year": 2025,
    "spotify": "0Y2jYeRtebUMr21kZwK2Fi"
  },
  "th9": {
    "title": "GO BESTFRIEND",
    "artist": "Roxy Dekker",
    "year": 2025,
    "spotify": "6sv1PdrGSGgWYzFqC5mruo"
  },
  "l4z": {
    "title": "Baila de Gasolina",
    "artist": "Effe Serieus",
    "year": 2025,
    "spotify": "43TPlT0l0HXLtKUOUoY3gY"
  },
  "csv": {
    "title": "Pasapas",
    "artist": "Kinderen voor Kinderen",
    "year": 2019,
    "spotify": "7G7xDVo2PIUOJVipYbe3bV"
  },
  "179": {
    "title": "Ola ole olee",
    "artist": "Kinderen voor Kinderen",
    "year": 2026,
    "spotify": "0Ul3G0uGWfI2qPYjVVv4ix"
  },
  "xm2": {
    "title": "Automatisch",
    "artist": "FLEMMING",
    "year": 2022,
    "spotify": "6mMVJJkpzL5r9OyqX7VzBk"
  },
  "gis": {
    "title": "Op een onbewoond eiland",
    "artist": "Kinderen voor Kinderen",
    "year": 2023,
    "spotify": "32riyrx24W3scOAT0q0kHH"
  },
  "7ex": {
    "title": "Avond4daagse",
    "artist": "Kinderen voor Kinderen",
    "year": 2022,
    "spotify": "5imoXApElqf4AO2qII2154"
  },
  "yda": {
    "title": "Worden wat je wil",
    "artist": "Kinderen voor Kinderen",
    "year": 2022,
    "spotify": "2inIv6fJb1YBOvuwgTTWD8"
  },
  "r98": {
    "title": "Favoriete knuffel",
    "artist": "Kinderen voor Kinderen",
    "year": 2022,
    "spotify": "4jl0Y6NggTUUwKJPcwOC9D"
  },
  "cxm": {
    "title": "De baas",
    "artist": "Kinderen voor Kinderen",
    "year": 2022,
    "spotify": "5kudQTiQLIKYyyjXYR1PVx"
  },
  "icd": {
    "title": "Elke dag jarig",
    "artist": "Kinderen voor Kinderen",
    "year": 2020,
    "spotify": "42OeDKQbAx0QH5zR8cKyas"
  },
  "zi3": {
    "title": "Zie je wel!",
    "artist": "Kinderen voor Kinderen",
    "year": 2020,
    "spotify": "1aSxBd2MjWMNXPojbOonYP"
  },
  "eds": {
    "title": "Andersom",
    "artist": "Kinderen voor Kinderen",
    "year": 2020,
    "spotify": "7luQdidDzQ6DaNBpD4uQ2J"
  },
  "w1l": {
    "title": "Ik ben een gamer",
    "artist": "Kinderen voor Kinderen",
    "year": 2020,
    "spotify": "5RaQKvQQUjMUz3fJuRi2RB"
  },
  "46y": {
    "title": "Al 40 jaar",
    "artist": "Kinderen voor Kinderen",
    "year": 2019,
    "spotify": "1ibJDeNHbQjKzwR2TcouAM"
  },
  "hv3": {
    "title": "Oeps!",
    "artist": "Kinderen voor Kinderen",
    "year": 2019,
    "spotify": "675RFOqDFZCM8M7XzTZX1M"
  },
  "t8r": {
    "title": "Baila De Utrecht",
    "artist": "Vrienden van FC Utrecht",
    "year": 2025,
    "spotify": "1si4C09HPkKIPmTV1l1Qfa"
  },
  "4pd": {
    "title": "Alles Op Gevoel",
    "artist": "FLEMMING & Zoë Tauran & Ronnie Flex",
    "year": 2024,
    "spotify": "2hCc09htDSAQobdmbYWryY"
  },
  "opy": {
    "title": "Amsterdam",
    "artist": "FLEMMING",
    "year": 2021,
    "spotify": "0GRc10CjRqO0wtXUnxR1uY"
  },
  "8b1": {
    "title": "Champie & Sashimi",
    "artist": "FLEMMING & Turfy Gang",
    "year": 2026
  },
  "lnx": {
    "title": "Onweer In M'n Hoofd",
    "artist": "FLEMMING",
    "year": 2024,
    "spotify": "7GyjwvMINxtagvYJN33O0p"
  },
  "qn5": {
    "title": "Tafel Voor 2",
    "artist": "FLEMMING",
    "year": 2024,
    "spotify": "0bAy8gfIx54HKQIsIiRju8"
  },
  "2h1": {
    "title": "1 Glas",
    "artist": "FLEMMING & Miss Montreal",
    "year": 2026
  }
}